ipywe/__init__.py
ipywe/_utils.py
ipywe/_version.py
ipywe/base.py
ipywe/example.py
ipywe/fileselector.py
ipywe/imagedisplay.py
ipywe/imageslider.py
ipywe/imgdatagraph.py
ipywe/tomvizjs.py
ipywe/vtkjs.py
ipywe/wizard.py
ipywe-0.1.3a1.data/data/share/jupyter/nbextensions/ipywe/extension.js
ipywe-0.1.3a1.data/data/share/jupyter/nbextensions/ipywe/index.js
ipywe-0.1.3a1.data/data/share/jupyter/nbextensions/ipywe/index.js.map
ipywe-0.1.3a1.dist-info/LICENSE
ipywe-0.1.3a1.dist-info/METADATA
ipywe-0.1.3a1.dist-info/WHEEL
ipywe-0.1.3a1.dist-info/top_level.txt
ipywe-0.1.3a1.dist-info/RECORD
