Metadata-Version: 2.1
Name: ipywe
Version: 0.1.3a1
Summary: ipywidgets extensions
Home-page: https://github.com/neutrons/ipywe
Author: ipywe team
Author-email: UNKNOWN
License: BSD
Keywords: ipython,jupyter,widgets,neutron
Platform: UNKNOWN
Classifier: Development Status :: 4 - Beta
Classifier: Framework :: IPython
Classifier: Intended Audience :: Developers
Classifier: Intended Audience :: Science/Research
Classifier: Topic :: Multimedia :: Graphics
Classifier: Programming Language :: Python :: 2
Classifier: Programming Language :: Python :: 2.7
Classifier: Programming Language :: Python :: 3
Classifier: Programming Language :: Python :: 3.3
Classifier: Programming Language :: Python :: 3.4
Classifier: Programming Language :: Python :: 3.5
Requires-Dist: ipywidgets (>=6.0.0)
Requires-Dist: traitlets
Requires-Dist: pillow
Requires-Dist: numpy
Requires-Dist: scipy
